Timeline_Manager/__init__.py
Timeline_Manager/module.py
Timeline_Manager-1.1.1.dist-info/LICENSE
Timeline_Manager-1.1.1.dist-info/METADATA
Timeline_Manager-1.1.1.dist-info/WHEEL
Timeline_Manager-1.1.1.dist-info/top_level.txt
Timeline_Manager-1.1.1.dist-info/RECORD
