Metadata-Version: 2.1
Name: Timeline-Manager
Version: 1.1.1
Summary: A job scheduling library that supports various time intervals
Home-page: https://github.com/anri-Tvalabeishvili/Timeline-Manager
Author: Anri Tvalabeishvili
Author-email: anri.tvalabeishvili@gmail.com
Project-URL: Documentation, https://timeline-manager.readthedocs.io/en/latest/index.html
Project-URL: HomePage, https://github.com/anri-Tvalabeishvili/Timeline-Manager
Project-URL: Tracker, https://github.com/anri-Tvalabeishvili/Timeline-Manager/issues
Classifier: Programming Language :: Python :: 3
Classifier: License :: OSI Approved :: MIT License
Classifier: Operating System :: OS Independent
Requires-Python: >=3.6
License-File: LICENSE
